odoo/addons/mrp_workorder_priority/README.rst
odoo/addons/mrp_workorder_priority/__init__.py
odoo/addons/mrp_workorder_priority/__manifest__.py
odoo/addons/mrp_workorder_priority/i18n/it.po
odoo/addons/mrp_workorder_priority/i18n/mrp_workorder_priority.pot
odoo/addons/mrp_workorder_priority/models/__init__.py
odoo/addons/mrp_workorder_priority/models/mrp_workorder.py
odoo/addons/mrp_workorder_priority/readme/CONTRIBUTORS.md
odoo/addons/mrp_workorder_priority/readme/DESCRIPTION.md
odoo/addons/mrp_workorder_priority/static/description/icon.png
odoo/addons/mrp_workorder_priority/static/description/index.html
odoo/addons/mrp_workorder_priority/views/mrp_workorder_views.xml
odoo_addon_mrp_workorder_priority-16.0.1.0.0.4.dist-info/METADATA
odoo_addon_mrp_workorder_priority-16.0.1.0.0.4.dist-info/WHEEL
odoo_addon_mrp_workorder_priority-16.0.1.0.0.4.dist-info/top_level.txt
odoo_addon_mrp_workorder_priority-16.0.1.0.0.4.dist-info/RECORD
